README.md
setup.py
gamechain_lobby/__init__.py
gamechain_lobby/addr_test.py
gamechain_lobby/async_test.py
gamechain_lobby/game_shelves.py
gamechain_lobby/gamechain_lobby.py
gamechain_lobby/gamechain_monitor.py
gamechain_lobby/gc_comm.py
gamechain_lobby/gcl_message.py
gamechain_lobby/gcl_message_builder.py
gamechain_lobby/gcl_parser.py
gamechain_lobby/message_monitors.py
gamechain_lobby/receive_test.py
gamechain_lobby/test_websockets.py
gamechain_lobby/txdeep_test.py
gamechain_lobby/utils.py
gamechain_lobby/verify_test.py
gamechain_lobby.egg-info/PKG-INFO
gamechain_lobby.egg-info/SOURCES.txt
gamechain_lobby.egg-info/dependency_links.txt
gamechain_lobby.egg-info/top_level.txt