Metadata-Version: 2.1
Name: gamechain-lobby
Version: 0.0.1
Summary: Game matchmaking on the BCH blockchain
Home-page: https://github.com/devalbo/gamechain-lobby
Author: Albert Boehmler
Author-email: ajboehmler@gmail.com
License: UNKNOWN
Platform: UNKNOWN
Classifier: Programming Language :: Python :: 3
Classifier: License :: OSI Approved :: GNU General Public License v3 (GPLv3)
Classifier: Operating System :: OS Independent
